[ {
  "@id" : "http://sem.stream.reasoning/frame/68",
  "@type" : [ "http://vision.semkg.org/onto/v0.1/Image" ],
  "http://vision.semkg.org/id" : [ {
    "@value" : "68"
  } ]
}, {
  "@id" : "http://sem.stream.reasoning/observation/68",
  "@type" : [ "http://www.w3.org/ns/sosa/Observation" ],
  "http://www.w3.org/ns/sosa/hasResult" : [ {
    "@id" : "http://vision.semkg.org/detection/d2a84d16-d93b-4cbe-889d-2431fafb53f6"
  }, {
    "@id" : "http://vision.semkg.org/detection/00735fe9-1f83-46c9-a7cf-3884be560664"
  }, {
    "@id" : "http://vision.semkg.org/detection/3b20038e-a3ee-4b25-98d0-2a6016d0e819"
  }, {
    "@id" : "http://vision.semkg.org/detection/4a61827c-f055-4d52-adc9-feeb4f0352b0"
  }, {
    "@id" : "http://vision.semkg.org/detection/eb905b77-f8ad-4042-b2a3-bb91c1efb88a"
  }, {
    "@id" : "http://vision.semkg.org/detection/51613cea-65aa-40c9-9bfa-79e920cb6fa4"
  }, {
    "@id" : "http://vision.semkg.org/detection/23d3608e-6ed2-4334-81a8-dba3231c427a"
  }, {
    "@id" : "http://vision.semkg.org/detection/5722797e-46e7-42f1-b14a-ca6358111a3e"
  } ],
  "http://www.w3.org/ns/sosa/usedProcedure" : [ {
    "@id" : "http://vision.semkg.org/detector/yolov4"
  } ]
}, {
  "@id" : "http://vision.semkg.org/box/16b950b9-3a55-4733-9193-fbdd3596d77a",
  "@type" : [ "http://vision.semkg.org/onto/v0.1/Box" ],
  "http://vision.semkg.org/onto/v0.1/centerX" : [ {
    "@type" : "http://www.w3.org/2001/XMLSchema#float",
    "@value" : "471.585"
  } ],
  "http://vision.semkg.org/onto/v0.1/centerY" : [ {
    "@type" : "http://www.w3.org/2001/XMLSchema#float",
    "@value" : "176.35501"
  } ],
  "http://vision.semkg.org/onto/v0.1/hasHeight" : [ {
    "@type" : "http://www.w3.org/2001/XMLSchema#float",
    "@value" : "12.610001"
  } ],
  "http://vision.semkg.org/onto/v0.1/hasWidth" : [ {
    "@type" : "http://www.w3.org/2001/XMLSchema#float",
    "@value" : "38.809998"
  } ]
}, {
  "@id" : "http://vision.semkg.org/box/321e3814-4d1b-442a-a385-e120966aac2c",
  "@type" : [ "http://vision.semkg.org/onto/v0.1/Box" ],
  "http://vision.semkg.org/onto/v0.1/centerX" : [ {
    "@type" : "http://www.w3.org/2001/XMLSchema#float",
    "@value" : "609.2576"
  } ],
  "http://vision.semkg.org/onto/v0.1/centerY" : [ {
    "@type" : "http://www.w3.org/2001/XMLSchema#float",
    "@value" : "198.05603"
  } ],
  "http://vision.semkg.org/onto/v0.1/hasHeight" : [ {
    "@type" : "http://www.w3.org/2001/XMLSchema#float",
    "@value" : "54.968826"
  } ],
  "http://vision.semkg.org/onto/v0.1/hasWidth" : [ {
    "@type" : "http://www.w3.org/2001/XMLSchema#float",
    "@value" : "55.151978"
  } ]
}, {
  "@id" : "http://vision.semkg.org/box/4ad6147c-42d5-4e6d-a8e2-eedaad89933c",
  "@type" : [ "http://vision.semkg.org/onto/v0.1/Box" ],
  "http://vision.semkg.org/onto/v0.1/centerX" : [ {
    "@type" : "http://www.w3.org/2001/XMLSchema#float",
    "@value" : "553.095"
  } ],
  "http://vision.semkg.org/onto/v0.1/centerY" : [ {
    "@type" : "http://www.w3.org/2001/XMLSchema#float",
    "@value" : "171.505"
  } ],
  "http://vision.semkg.org/onto/v0.1/hasHeight" : [ {
    "@type" : "http://www.w3.org/2001/XMLSchema#float",
    "@value" : "10.669998"
  } ],
  "http://vision.semkg.org/onto/v0.1/hasWidth" : [ {
    "@type" : "http://www.w3.org/2001/XMLSchema#float",
    "@value" : "15.529968"
  } ]
}, {
  "@id" : "http://vision.semkg.org/box/811705a1-15b9-4ae6-8d6f-08577274c7f4",
  "@type" : [ "http://vision.semkg.org/onto/v0.1/Box" ],
  "http://vision.semkg.org/onto/v0.1/centerX" : [ {
    "@type" : "http://www.w3.org/2001/XMLSchema#float",
    "@value" : "40.210815"
  } ],
  "http://vision.semkg.org/onto/v0.1/centerY" : [ {
    "@type" : "http://www.w3.org/2001/XMLSchema#float",
    "@value" : "185.44899"
  } ],
  "http://vision.semkg.org/onto/v0.1/hasHeight" : [ {
    "@type" : "http://www.w3.org/2001/XMLSchema#float",
    "@value" : "42.69104"
  } ],
  "http://vision.semkg.org/onto/v0.1/hasWidth" : [ {
    "@type" : "http://www.w3.org/2001/XMLSchema#float",
    "@value" : "80.42163"
  } ]
}, {
  "@id" : "http://vision.semkg.org/box/97ff061a-bd79-42dc-aca5-f338adfc45ad",
  "@type" : [ "http://vision.semkg.org/onto/v0.1/Box" ],
  "http://vision.semkg.org/onto/v0.1/centerX" : [ {
    "@type" : "http://www.w3.org/2001/XMLSchema#float",
    "@value" : "722.1726"
  } ],
  "http://vision.semkg.org/onto/v0.1/centerY" : [ {
    "@type" : "http://www.w3.org/2001/XMLSchema#float",
    "@value" : "186.35876"
  } ],
  "http://vision.semkg.org/onto/v0.1/hasHeight" : [ {
    "@type" : "http://www.w3.org/2001/XMLSchema#float",
    "@value" : "20.459274"
  } ],
  "http://vision.semkg.org/onto/v0.1/hasWidth" : [ {
    "@type" : "http://www.w3.org/2001/XMLSchema#float",
    "@value" : "7.9107056"
  } ]
}, {
  "@id" : "http://vision.semkg.org/box/cd24a7b7-69e5-4748-b974-322e2493d647",
  "@type" : [ "http://vision.semkg.org/onto/v0.1/Box" ],
  "http://vision.semkg.org/onto/v0.1/centerX" : [ {
    "@type" : "http://www.w3.org/2001/XMLSchema#float",
    "@value" : "374.76825"
  } ],
  "http://vision.semkg.org/onto/v0.1/centerY" : [ {
    "@type" : "http://www.w3.org/2001/XMLSchema#float",
    "@value" : "181.06664"
  } ],
  "http://vision.semkg.org/onto/v0.1/hasHeight" : [ {
    "@type" : "http://www.w3.org/2001/XMLSchema#float",
    "@value" : "16.787384"
  } ],
  "http://vision.semkg.org/onto/v0.1/hasWidth" : [ {
    "@type" : "http://www.w3.org/2001/XMLSchema#float",
    "@value" : "26.480743"
  } ]
}, {
  "@id" : "http://vision.semkg.org/box/de0750a0-171d-4b54-8e90-1caa40daaede",
  "@type" : [ "http://vision.semkg.org/onto/v0.1/Box" ],
  "http://vision.semkg.org/onto/v0.1/centerX" : [ {
    "@type" : "http://www.w3.org/2001/XMLSchema#float",
    "@value" : "320.1369"
  } ],
  "http://vision.semkg.org/onto/v0.1/centerY" : [ {
    "@type" : "http://www.w3.org/2001/XMLSchema#float",
    "@value" : "183.47163"
  } ],
  "http://vision.semkg.org/onto/v0.1/hasHeight" : [ {
    "@type" : "http://www.w3.org/2001/XMLSchema#float",
    "@value" : "21.595825"
  } ],
  "http://vision.semkg.org/onto/v0.1/hasWidth" : [ {
    "@type" : "http://www.w3.org/2001/XMLSchema#float",
    "@value" : "40.63443"
  } ]
}, {
  "@id" : "http://vision.semkg.org/box/fa7bb7e9-b52c-4826-a21a-019448a9be30",
  "@type" : [ "http://vision.semkg.org/onto/v0.1/Box" ],
  "http://vision.semkg.org/onto/v0.1/centerX" : [ {
    "@type" : "http://www.w3.org/2001/XMLSchema#float",
    "@value" : "351.62143"
  } ],
  "http://vision.semkg.org/onto/v0.1/centerY" : [ {
    "@type" : "http://www.w3.org/2001/XMLSchema#float",
    "@value" : "180.96848"
  } ],
  "http://vision.semkg.org/onto/v0.1/hasHeight" : [ {
    "@type" : "http://www.w3.org/2001/XMLSchema#float",
    "@value" : "20.604034"
  } ],
  "http://vision.semkg.org/onto/v0.1/hasWidth" : [ {
    "@type" : "http://www.w3.org/2001/XMLSchema#float",
    "@value" : "36.293762"
  } ]
}, {
  "@id" : "http://vision.semkg.org/detection/00735fe9-1f83-46c9-a7cf-3884be560664",
  "@type" : [ "http://vision.semkg.org/onto/v0.1/Detection", "http://www.w3.org/ns/sosa/Result" ],
  "http://vision.semkg.org/box" : [ {
    "@id" : "http://vision.semkg.org/box/4ad6147c-42d5-4e6d-a8e2-eedaad89933c"
  } ],
  "http://vision.semkg.org/onto/v0.1/hasDetectionScore" : [ {
    "@type" : "http://www.w3.org/2001/XMLSchema#float",
    "@value" : "0.9"
  } ],
  "http://vision.semkg.org/onto/v0.1/isDetectedBy" : [ {
    "@id" : "http://vision.semkg.org/detector/yolov4"
  } ],
  "http://vision.semkg.org/onto/v0.1/isDetectionOf" : [ {
    "@id" : "http://sem.stream.reasoning/frame/68"
  } ]
}, {
  "@id" : "http://vision.semkg.org/detection/23d3608e-6ed2-4334-81a8-dba3231c427a",
  "@type" : [ "http://vision.semkg.org/onto/v0.1/Detection", "http://www.w3.org/ns/sosa/Result" ],
  "http://vision.semkg.org/box" : [ {
    "@id" : "http://vision.semkg.org/box/321e3814-4d1b-442a-a385-e120966aac2c"
  } ],
  "http://vision.semkg.org/onto/v0.1/hasDetectionScore" : [ {
    "@type" : "http://www.w3.org/2001/XMLSchema#float",
    "@value" : "0.9"
  } ],
  "http://vision.semkg.org/onto/v0.1/isDetectedBy" : [ {
    "@id" : "http://vision.semkg.org/detector/yolov4"
  } ],
  "http://vision.semkg.org/onto/v0.1/isDetectionOf" : [ {
    "@id" : "http://sem.stream.reasoning/frame/68"
  } ]
}, {
  "@id" : "http://vision.semkg.org/detection/3b20038e-a3ee-4b25-98d0-2a6016d0e819",
  "@type" : [ "http://vision.semkg.org/onto/v0.1/Detection", "http://www.w3.org/ns/sosa/Result" ],
  "http://vision.semkg.org/box" : [ {
    "@id" : "http://vision.semkg.org/box/de0750a0-171d-4b54-8e90-1caa40daaede"
  } ],
  "http://vision.semkg.org/onto/v0.1/hasDetectionScore" : [ {
    "@type" : "http://www.w3.org/2001/XMLSchema#float",
    "@value" : "0.9"
  } ],
  "http://vision.semkg.org/onto/v0.1/isDetectedBy" : [ {
    "@id" : "http://vision.semkg.org/detector/yolov4"
  } ],
  "http://vision.semkg.org/onto/v0.1/isDetectionOf" : [ {
    "@id" : "http://sem.stream.reasoning/frame/68"
  } ]
}, {
  "@id" : "http://vision.semkg.org/detection/4a61827c-f055-4d52-adc9-feeb4f0352b0",
  "@type" : [ "http://vision.semkg.org/onto/v0.1/Detection", "http://www.w3.org/ns/sosa/Result" ],
  "http://vision.semkg.org/box" : [ {
    "@id" : "http://vision.semkg.org/box/fa7bb7e9-b52c-4826-a21a-019448a9be30"
  } ],
  "http://vision.semkg.org/onto/v0.1/hasDetectionScore" : [ {
    "@type" : "http://www.w3.org/2001/XMLSchema#float",
    "@value" : "0.9"
  } ],
  "http://vision.semkg.org/onto/v0.1/isDetectedBy" : [ {
    "@id" : "http://vision.semkg.org/detector/yolov4"
  } ],
  "http://vision.semkg.org/onto/v0.1/isDetectionOf" : [ {
    "@id" : "http://sem.stream.reasoning/frame/68"
  } ]
}, {
  "@id" : "http://vision.semkg.org/detection/51613cea-65aa-40c9-9bfa-79e920cb6fa4",
  "@type" : [ "http://vision.semkg.org/onto/v0.1/Detection", "http://www.w3.org/ns/sosa/Result" ],
  "http://vision.semkg.org/box" : [ {
    "@id" : "http://vision.semkg.org/box/cd24a7b7-69e5-4748-b974-322e2493d647"
  } ],
  "http://vision.semkg.org/onto/v0.1/hasDetectionScore" : [ {
    "@type" : "http://www.w3.org/2001/XMLSchema#float",
    "@value" : "0.9"
  } ],
  "http://vision.semkg.org/onto/v0.1/isDetectedBy" : [ {
    "@id" : "http://vision.semkg.org/detector/yolov4"
  } ],
  "http://vision.semkg.org/onto/v0.1/isDetectionOf" : [ {
    "@id" : "http://sem.stream.reasoning/frame/68"
  } ]
}, {
  "@id" : "http://vision.semkg.org/detection/5722797e-46e7-42f1-b14a-ca6358111a3e",
  "@type" : [ "http://vision.semkg.org/onto/v0.1/Detection", "http://www.w3.org/ns/sosa/Result" ],
  "http://vision.semkg.org/box" : [ {
    "@id" : "http://vision.semkg.org/box/97ff061a-bd79-42dc-aca5-f338adfc45ad"
  } ],
  "http://vision.semkg.org/onto/v0.1/hasDetectionScore" : [ {
    "@type" : "http://www.w3.org/2001/XMLSchema#float",
    "@value" : "0.9"
  } ],
  "http://vision.semkg.org/onto/v0.1/isDetectedBy" : [ {
    "@id" : "http://vision.semkg.org/detector/yolov4"
  } ],
  "http://vision.semkg.org/onto/v0.1/isDetectionOf" : [ {
    "@id" : "http://sem.stream.reasoning/frame/68"
  } ]
}, {
  "@id" : "http://vision.semkg.org/detection/d2a84d16-d93b-4cbe-889d-2431fafb53f6",
  "@type" : [ "http://vision.semkg.org/onto/v0.1/Detection", "http://www.w3.org/ns/sosa/Result" ],
  "http://vision.semkg.org/box" : [ {
    "@id" : "http://vision.semkg.org/box/16b950b9-3a55-4733-9193-fbdd3596d77a"
  } ],
  "http://vision.semkg.org/onto/v0.1/hasDetectionScore" : [ {
    "@type" : "http://www.w3.org/2001/XMLSchema#float",
    "@value" : "0.9"
  } ],
  "http://vision.semkg.org/onto/v0.1/isDetectedBy" : [ {
    "@id" : "http://vision.semkg.org/detector/yolov4"
  } ],
  "http://vision.semkg.org/onto/v0.1/isDetectionOf" : [ {
    "@id" : "http://sem.stream.reasoning/frame/68"
  } ]
}, {
  "@id" : "http://vision.semkg.org/detection/eb905b77-f8ad-4042-b2a3-bb91c1efb88a",
  "@type" : [ "http://vision.semkg.org/onto/v0.1/Detection", "http://www.w3.org/ns/sosa/Result" ],
  "http://vision.semkg.org/box" : [ {
    "@id" : "http://vision.semkg.org/box/811705a1-15b9-4ae6-8d6f-08577274c7f4"
  } ],
  "http://vision.semkg.org/onto/v0.1/hasDetectionScore" : [ {
    "@type" : "http://www.w3.org/2001/XMLSchema#float",
    "@value" : "0.9"
  } ],
  "http://vision.semkg.org/onto/v0.1/isDetectedBy" : [ {
    "@id" : "http://vision.semkg.org/detector/yolov4"
  } ],
  "http://vision.semkg.org/onto/v0.1/isDetectionOf" : [ {
    "@id" : "http://sem.stream.reasoning/frame/68"
  } ]
}, {
  "@id" : "http://vision.semkg.org/detector/yolov4",
  "@type" : [ "http://vision.semkg.org/onto/v0.1/Detector", "http://www.w3.org/ns/sosa/Procedure" ]
} ]